himile_util/__init__.py
himile_util/himile_log.py
himile_util/himile_util.py
himile_util/himile_db/__init__.py
himile_util/himile_db/db_pool.py
himile_util/himile_db/oracle_db_pool.py
himile_util-0.4.0.dist-info/METADATA
himile_util-0.4.0.dist-info/WHEEL
himile_util-0.4.0.dist-info/top_level.txt
himile_util-0.4.0.dist-info/RECORD
