Metadata-Version: 2.4
Name: himile_util
Version: 0.4.0
Summary: A HIMILE utils package
Author-email: qhw <20244111@himile.net>
Requires-Python: >=3.10
Requires-Dist: aiomysql>=0.2.0
Requires-Dist: PyYAML>=6.0.2
Requires-Dist: starlette>=0.46.2
Requires-Dist: fastapi>=0.115.12
Requires-Dist: loguru>=0.7.3
Requires-Dist: openai>=1.64.0
Requires-Dist: aiofiles>=24.1.0
Requires-Dist: aiomysql>=0.2.0
Requires-Dist: dbutils>=3.1.0
Requires-Dist: mysql-connector-python>=9.2.0
Requires-Dist: numpy<2.0.0,>=1.24.4
Requires-Dist: oracledb>=3.2.0
